mercapy/__init__.py
mercapy/constants.py
mercapy/merca.py
mercapy/elements/__init__.py
mercapy/elements/base.py
mercapy/elements/category.py
mercapy/elements/photo.py
mercapy/elements/product.py
mercapy/elements/season.py
mercapy/utils/__init__.py
mercapy/utils/api.py
mercapy/utils/urls.py
mercapy/utils/warehouses.py
mercapy-1.0.3.dist-info/LICENSE
mercapy-1.0.3.dist-info/METADATA
mercapy-1.0.3.dist-info/WHEEL
mercapy-1.0.3.dist-info/top_level.txt
mercapy-1.0.3.dist-info/RECORD
