Metadata-Version: 2.1
Name: mercapy
Version: 1.0.3
Summary: A Mercadona interface for Python to track product prices, amounts, and more.
Author: Joel Taylor
Author-email: contact@joeltaylor.business
License: MIT
Keywords: mercadona,api,sdk,data science,prices,information
Classifier: License :: OSI Approved :: MIT License
Classifier: Programming Language :: Python
Classifier: Programming Language :: Python :: 3.12
Classifier: Programming Language :: Python :: Implementation :: CPython
License-File: LICENSE
Requires-Dist: requests
